pyecowatt/__init__.py
pyecowatt/pyecowatt.py
pyecowatt-0.1.10.dist-info/METADATA
pyecowatt-0.1.10.dist-info/WHEEL
pyecowatt-0.1.10.dist-info/top_level.txt
pyecowatt-0.1.10.dist-info/RECORD
